dbx_test/__init__.py
dbx_test/artifacts.py
dbx_test/bundle.py
dbx_test/cli.py
dbx_test/config.py
dbx_test/discovery.py
dbx_test/notebook_runner.py
dbx_test/reporting.py
dbx_test/runner_remote.py
dbx_test/testing.py
dbx_test/utils/__init__.py
dbx_test/utils/databricks.py
dbx_test/utils/notebook.py
dbx_test/utils/validation.py
dbx_test-0.1.0.dist-info/licenses/LICENSE
dbx_test-0.1.0.dist-info/METADATA
dbx_test-0.1.0.dist-info/WHEEL
dbx_test-0.1.0.dist-info/entry_points.txt
dbx_test-0.1.0.dist-info/top_level.txt
dbx_test-0.1.0.dist-info/RECORD
