Metadata-Version: 2.4
Name: dbx_test
Version: 0.1.0
Summary: Serverless-first testing framework for Databricks notebooks with Asset Bundle support
Author-email: James Parham <james.parham@databricks.com>
License: MIT
Project-URL: Homepage, https://github.com/jsparhamii/dbx_test
Project-URL: Documentation, https://github.com/jsparhamii/dbx_test/tree/main/docs
Project-URL: Repository, https://github.com/jsparhamii/dbx_test
Project-URL: Issues, https://github.com/jsparhamii/dbx_test/issues
Keywords: databricks,testing,notebooks,unit-testing,spark,serverless,asset-bundles
Classifier: Development Status :: 4 - Beta
Classifier: Intended Audience :: Developers
Classifier: License :: OSI Approved :: MIT License
Classifier: Programming Language :: Python :: 3
Classifier: Programming Language :: Python :: 3.10
Classifier: Programming Language :: Python :: 3.11
Classifier: Programming Language :: Python :: 3.12
Classifier: Topic :: Software Development :: Testing
Classifier: Topic :: Software Development :: Libraries :: Python Modules
Requires-Python: >=3.10
License-File: LICENSE
Requires-Dist: databricks-sdk>=0.20.0
Requires-Dist: pyyaml>=6.0
Requires-Dist: junit-xml>=1.9
Requires-Dist: rich>=13.0.0
Requires-Dist: click>=8.0.0
Requires-Dist: nbformat>=5.0.0
Requires-Dist: requests>=2.31.0
Provides-Extra: dev
Requires-Dist: pytest>=7.0.0; extra == "dev"
Requires-Dist: pytest-cov>=4.0.0; extra == "dev"
Requires-Dist: black>=23.0.0; extra == "dev"
Requires-Dist: flake8>=6.0.0; extra == "dev"
Requires-Dist: mypy>=1.0.0; extra == "dev"
Requires-Dist: build>=1.0.0; extra == "dev"
Dynamic: license-file
